strongly_typed/__init__.py
strongly_typed/__test__.py
strongly_typed-1.0.1.post3.dist-info/METADATA
strongly_typed-1.0.1.post3.dist-info/WHEEL
strongly_typed-1.0.1.post3.dist-info/RECORD
