Metadata-Version: 2.1
Name: strongly-typed
Version: 1.0.1.post3
Summary: Python module to enforce strong typing
License: Apache-2.0
Author: TheTechRobo
Author-email: thetechrobo@proton.me
Requires-Python: >=3.8,<4.0
Classifier: License :: OSI Approved :: Apache Software License
Classifier: Programming Language :: Python :: 3
Classifier: Programming Language :: Python :: 3.8
Classifier: Programming Language :: Python :: 3.9
Classifier: Programming Language :: Python :: 3.10
Classifier: Programming Language :: Python :: 3.11
Project-URL: repository, https://github.com/TheTechRobo/strongly-typed
